chx/gh/__init__.py
chx/gh/__main__.py
chx/gh/api.py
chx_gh-0.0.2.dist-info/METADATA
chx_gh-0.0.2.dist-info/WHEEL
chx_gh-0.0.2.dist-info/top_level.txt
chx_gh-0.0.2.dist-info/RECORD
