Metadata-Version: 2.1
Name: chx-gh
Version: 0.0.2
Summary: Github 命令行工具
Home-page: https://github.com/chenxizhan1995/gh.git
Author: Xizhan Chen
Author-email: chenxizhan1995@163.com
License: UNKNOWN
Platform: UNKNOWN
Classifier: Programming Language :: Python :: 3
Classifier: License :: OSI Approved :: MIT License
Classifier: Operating System :: OS Independent
Requires-Python: >=3.6
